Workbook

Sheet README
A1: Airand — Unit Economics & Break-even Model
A2: Phase 2 — Problem & Market Validation · Draft v0.1 · 5 October 2026
A4: Purpose | B4: Tests whether a zone-based bicycle delivery pool can deliver at a fixed ₦700–₦1,000 rate and cover its costs. Every number is an assumption unless a source is named on the Assumptions sheet.
A5: How to use | B5: Change blue cells on the Assumptions sheet only. All other sheets recalculate. Yellow cells are the three levers that decide viability: zone rate, cyclist wage, deliveries per cyclist per shift.
A6: Colour legend | B6: Blue text = input you can change · Black = formula · Green = link to another sheet · Yellow fill = key lever.
A7: Evidence labels | B7: [Source] cited external page · [Assumption] founder or analyst estimate · [Placeholder] number unknown, set to a plausible value for the model to run.
A8: Sheets | B8: Assumptions → Cyclist Economics → Zone P&L → Sensitivity → Competitor Check
A9: Caveat | B9: This is a portfolio demonstration model built on public benchmarks and labelled estimates. It is not a forecast of an operating business.

Sheet Assumptions
A1: Assumptions
A2: Change blue cells only. Yellow = key lever.
A4: Ref | B4: Assumption | C4: Value | D4: Unit | E4: Label | F4: Basis / source
A5: PRICING
A6: P1 | B6: Fixed zone rate per delivery | C6: 900 | D6: ₦ | E6: [Assumption] | F6: Target band ₦700–₦1,000 from Market Research price comparison (undercut Bolt Send off-peak est. ₦800–₦1,500)
A7: P2 | B7: Share of deliveries that fail or are written off | C7: 0.01 | D7: % | E7: [Assumption] | F7: Analyst estimate; no revenue on failed deliveries
A8: P3 | B8: Messaging cost per delivery (WhatsApp/SMS code + tracking link) | C8: 10 | D8: ₦ | E8: [Assumption] | F8: Approximate Nigerian SMS/WhatsApp Business per-message cost
A9: CYCLISTS
A10: C1 | B10: Number of cyclists in the zone | C10: 10 | D10: cyclists | E10: [Source] | F10: Airand business plan (2025): 10 cyclists at launch
A11: C2 | B11: Cyclist wage per month | C11: 60000 | D11: ₦ | E11: [Assumption] | F11: Below motorbike dispatch benchmark of ₦90,000/month (Jobberman, Port Harcourt, 2026) — no fuel or licence
A12: C3 | B12: Working days per cyclist per month | C12: 26 | D12: days | E12: [Assumption] | F12: Six-day week
A13: C4 | B13: Shift length | C13: 8 | D13: hours | E13: [Assumption] | F13: Covers afternoon to 11 PM peak
A14: C5 | B14: Bicycle purchase cost | C14: 120000 | D14: ₦ | E14: [Assumption] | F14: Mid-range utility bicycle, Nigerian retail estimate
A15: C6 | B15: Bicycle useful life | C15: 24 | D15: months | E15: [Assumption] | F15: Straight-line depreciation
A16: C7 | B16: Bicycle maintenance per month | C16: 3000 | D16: ₦ | E16: [Assumption] | F16: Tyres, chain, brakes
A17: C8 | B17: Insulated bag + uniform + lights per cyclist | C17: 30000 | D17: ₦ | E17: [Assumption] | F17: Replaced every 12 months
A18: C9 | B18: Kit replacement cycle | C18: 12 | D18: months | E18: [Assumption]
A19: C10 | B19: Phone data allowance per cyclist per month | C19: 5000 | D19: ₦ | E19: [Assumption] | F19: Cyclist app needs data
A20: OPERATIONS
A21: O1 | B21: Average one-way trip distance (hub → vendor → receiver) | C21: 2.5 | D21: km | E21: [Assumption] | F21: Zone radius 2–3 km from Business Understanding Document
A22: O2 | B22: Average cycling speed in traffic | C22: 12 | D22: km/h | E22: [Assumption] | F22: Urban bicycle average
A23: O3 | B23: Return distance to hub or next pickup | C23: 2 | D23: km | E23: [Assumption] | F23: Shorter than outbound: next pickup is often nearer than the hub
A24: O4 | B24: Handover time (pickup + drop-off + code entry) | C24: 8 | D24: min | E24: [Assumption]
A25: O5 | B25: Utilisation (share of shift spent on deliveries) | C25: 0.45 | D25: % | E25: [Assumption] | F25: Demand is peaky; cyclists idle off-peak. Key lever.
A26: FIXED COSTS
A27: F1 | B27: Operations officer salary per month | C27: 120000 | D27: ₦ | E27: [Assumption] | F27: One dispatcher per zone
A28: F2 | B28: Hub point rent per month | C28: 40000 | D28: ₦ | E28: [Assumption] | F28: Small shared space or arrangement with anchor vendor
A29: F3 | B29: Platform hosting & software per month | C29: 50000 | D29: ₦ | E29: [Assumption] | F29: Cloud hosting, maps API, messaging gateway subscription
A30: F4 | B30: Marketing per month | C30: 20000 | D30: ₦ | E30: [Source] | F30: Airand plan: flyers ₦10,000 per 500; doubled for ongoing push
A31: F5 | B31: NIPOST CLRD Regional licence per year | C31: 500000 | D31: ₦ | E31: [Placeholder] | F31: Fee not published on clrd.nipost.gov.ng; Regional (South-East) category required because Airand delivers for third parties
A32: F6 | B32: CAC incorporation (one-off, amortised over 12 months) | C32: 60000 | D32: ₦ | E32: [Placeholder] | F32: Pre-condition for CLRD licence
A33: F7 | B33: Insurance, contingency per month | C33: 25000 | D33: ₦ | E33: [Assumption] | F33: Cyclist accident cover, theft
A34: DEMAND SCENARIOS
A35: D1 | B35: Vendors in zone — Low | C35: 6 | D35: vendors | E35: [Assumption] | F35: Lower end of 6–10 cluster
A36: D2 | B36: Vendors in zone — Base | C36: 8 | D36: vendors | E36: [Assumption]
A37: D3 | B37: Vendors in zone — High | C37: 10 | D37: vendors | E37: [Source] | F37: Airand plan: 10 partners by month 3
A38: D4 | B38: Deliveries per vendor per day — Low | C38: 5 | D38: deliveries | E38: [Assumption] | F38: Small buka, mostly walk-in
A39: D5 | B39: Deliveries per vendor per day — Base | C39: 8 | D39: deliveries | E39: [Assumption]
A40: D6 | B40: Deliveries per vendor per day — High | C40: 12 | D40: deliveries | E40: [Assumption] | F40: Busy nightlife vendor
A41: D7 | B41: Days vendors operate per month | C41: 26 | D41: days | E41: [Assumption]

Sheet Cyclist Economics
A1: Cyclist Economics — cost per cyclist per day and deliveries per shift
A2: All cells are formulas linked to Assumptions (green).
A4: Cost per cyclist per month
A5: Wage | B5: =Assumptions!$C$11 -> 60000
A6: Bicycle depreciation | B6: =Assumptions!$C$14/Assumptions!$C$15 -> 5000
A7: Bicycle maintenance | B7: =Assumptions!$C$16 -> 3000
A8: Kit (bag, uniform, lights) | B8: =Assumptions!$C$17/Assumptions!$C$18 -> 2500
A9: Phone data | B9: =Assumptions!$C$19 -> 5000
A10: Total cost per cyclist per month | B10: =SUM(B5:B9) -> 75500
A11: Total cost per cyclist per working day | B11: =B10/Assumptions!$C$12 -> 2903.8462
A13: Capacity per cyclist per shift
A14: Cycle time per delivery (minutes) | B14: =(Assumptions!$C$21+Assumptions!$C$23)/Assumptions!$C$22*60+Assumptions!$C$24 -> 30.5
A15: Theoretical deliveries per shift (100% busy) | B15: =Assumptions!$C$13*60/B14 -> 15.737705
A16: Expected deliveries per shift at assumed utilisation | B16: =B15*Assumptions!$C$25 -> 7.0819672
A18: Unit cost
A19: Cyclist cost per delivery at expected utilisation | B19: =IF(B16=0,0,B11/B16) -> 410.03383
A20: Messaging cost per delivery | B20: =Assumptions!$C$8 -> 10
A21: Direct cost per delivery (cyclist + messaging) | B21: =B19+B20 -> 420.03383
A22: Zone rate | B22: =Assumptions!$C$6 -> 900
A23: Contribution per delivery before fixed costs | B23: =B22*(1-Assumptions!$C$7)-B21 -> 470.96617
A24: Contribution margin | B24: =IF(B22=0,0,B23/B22) -> 0.52329574
A26: Break-even on cyclist cost alone
A27: Deliveries per cyclist per day needed to cover that cyclist | B27: =IF((Assumptions!$C$6*(1-Assumptions!$C$7)-Assumptions!$C$8)<=0,0,B11/(Assumptions!$C$6*(1-Assumptions!$C$7)-Assumptions!$C$8)) -> 3.2960796
A28: Utilisation that implies | B28: =IF(B15=0,0,B27/B15) -> 0.20943839

Sheet Zone P&L
A1: Zone P&L — monthly, three demand scenarios
A2: Low / Base / High combine the vendor count and deliveries-per-vendor scenarios on Assumptions.
A4: Line (₦ per month unless stated) | B4: Low | C4: Base | D4: High
A5: Demand
A6: Vendors in zone | B6: =Assumptions!$C$35 -> 6 | C6: =Assumptions!$C$36 -> 8 | D6: =Assumptions!$C$37 -> 10
A7: Deliveries per vendor per day | B7: =Assumptions!$C$38 -> 5 | C7: =Assumptions!$C$39 -> 8 | D7: =Assumptions!$C$40 -> 12
A8: Deliveries per day (zone) | B8: =B6*B7 -> 30 | C8: =C6*C7 -> 64 | D8: =D6*D7 -> 120
A9: Deliveries per month | B9: =B8*Assumptions!$C$41 -> 780 | C9: =C8*Assumptions!$C$41 -> 1664 | D9: =D8*Assumptions!$C$41 -> 3120
A10: Deliveries per cyclist per day | B10: =B8/Assumptions!$C$10 -> 3 | C10: =C8/Assumptions!$C$10 -> 6.4 | D10: =D8/Assumptions!$C$10 -> 12
A11: Capacity check: utilisation required | B11: =IF('Cyclist Economics'!$B$15=0,0,B10/'Cyclist Economics'!$B$15) -> 0.190625 | C11: =IF('Cyclist Economics'!$B$15=0,0,C10/'Cyclist Economics'!$B$15) -> 0.40666667 | D11: =IF('Cyclist Economics'!$B$15=0,0,D10/'Cyclist Economics'!$B$15) -> 0.7625
A13: Revenue
A14: Completed deliveries | B14: =B9*(1-Assumptions!$C$7) -> 772.2 | C14: =C9*(1-Assumptions!$C$7) -> 1647.36 | D14: =D9*(1-Assumptions!$C$7) -> 3088.8
A15: Delivery revenue | B15: =B14*Assumptions!$C$6 -> 694980 | C15: =C14*Assumptions!$C$6 -> 1482624 | D15: =D14*Assumptions!$C$6 -> 2779920
A17: Variable costs
A18: Messaging | B18: =B9*Assumptions!$C$8 -> 7800 | C18: =C9*Assumptions!$C$8 -> 16640 | D18: =D9*Assumptions!$C$8 -> 31200
A20: Cyclist costs
A21: Cyclist pool (all cyclists, fixed per month) | B21: ='Cyclist Economics'!$B$10*Assumptions!$C$10 -> 755000 | C21: ='Cyclist Economics'!$B$10*Assumptions!$C$10 -> 755000 | D21: ='Cyclist Economics'!$B$10*Assumptions!$C$10 -> 755000
A23: Fixed costs
A24: Operations officer | B24: =Assumptions!$C$27 -> 120000 | C24: =Assumptions!$C$27 -> 120000 | D24: =Assumptions!$C$27 -> 120000
A25: Hub rent | B25: =Assumptions!$C$28 -> 40000 | C25: =Assumptions!$C$28 -> 40000 | D25: =Assumptions!$C$28 -> 40000
A26: Platform & software | B26: =Assumptions!$C$29 -> 50000 | C26: =Assumptions!$C$29 -> 50000 | D26: =Assumptions!$C$29 -> 50000
A27: Marketing | B27: =Assumptions!$C$30 -> 20000 | C27: =Assumptions!$C$30 -> 20000 | D27: =Assumptions!$C$30 -> 20000
A28: CLRD licence (annual ÷ 12) | B28: =Assumptions!$C$31/12 -> 41666.667 | C28: =Assumptions!$C$31/12 -> 41666.667 | D28: =Assumptions!$C$31/12 -> 41666.667
A29: CAC incorporation (amortised) | B29: =Assumptions!$C$32/12 -> 5000 | C29: =Assumptions!$C$32/12 -> 5000 | D29: =Assumptions!$C$32/12 -> 5000
A30: Insurance & contingency | B30: =Assumptions!$C$33 -> 25000 | C30: =Assumptions!$C$33 -> 25000 | D30: =Assumptions!$C$33 -> 25000
A31: Total fixed costs | B31: =SUM(B24:B30) -> 301666.67 | C31: =SUM(C24:C30) -> 301666.67 | D31: =SUM(D24:D30) -> 301666.67
A33: Result
A34: Total costs | B34: =B18+B21+B31 -> 1064466.7 | C34: =C18+C21+C31 -> 1073306.7 | D34: =D18+D21+D31 -> 1087866.7
A35: Operating profit / (loss) | B35: =B15-B34 -> -369486.67 | C35: =C15-C34 -> 409317.33 | D35: =D15-D34 -> 1692053.3
A36: Operating margin | B36: =IF(B15=0,0,B35/B15) -> -0.53165079 | C36: =IF(C15=0,0,C35/C15) -> 0.27607629 | D36: =IF(D15=0,0,D35/D15) -> 0.60866979
A37: All-in cost per delivery | B37: =IF(B14=0,0,B34/B14) -> 1378.4857 | C37: =IF(C14=0,0,C34/C14) -> 651.53134 | D37: =IF(D14=0,0,D34/D14) -> 352.19719
A39: Break-even
A40: Monthly cost base excluding messaging | B40: =B21+B31 -> 1056666.7 | C40: =C21+C31 -> 1056666.7 | D40: =D21+D31 -> 1056666.7
A41: Net revenue per delivery (rate × completion − messaging) | B41: =Assumptions!$C$6*(1-Assumptions!$C$7)-Assumptions!$C$8 -> 881 | C41: =Assumptions!$C$6*(1-Assumptions!$C$7)-Assumptions!$C$8 -> 881 | D41: =Assumptions!$C$6*(1-Assumptions!$C$7)-Assumptions!$C$8 -> 881
A42: Break-even deliveries per month | B42: =IF(B41<=0,0,B40/B41) -> 1199.3946 | C42: =IF(C41<=0,0,C40/C41) -> 1199.3946 | D42: =IF(D41<=0,0,D40/D41) -> 1199.3946
A43: Break-even deliveries per day (zone) | B43: =B42/Assumptions!$C$41 -> 46.130563 | C43: =C42/Assumptions!$C$41 -> 46.130563 | D43: =D42/Assumptions!$C$41 -> 46.130563
A44: Break-even deliveries per cyclist per day | B44: =B43/Assumptions!$C$10 -> 4.6130563 | C44: =C43/Assumptions!$C$10 -> 4.6130563 | D44: =D43/Assumptions!$C$10 -> 4.6130563
A45: Headroom: scenario deliveries/day vs break-even | B45: =B8-B43 -> -16.130563 | C45: =C8-C43 -> 17.869437 | D45: =D8-D43 -> 73.869437

Sheet Sensitivity
A1: Sensitivity — operating profit per month (₦) by zone rate and deliveries per cyclist per day
A2: Each cell recomputes the full monthly P&L for that rate and volume; cyclist count and fixed costs from Assumptions. Negative = loss.
A4: Deliveries / cyclist / day ↓ Zone rate → | B4: 600 | C4: 700 | D4: 800 | E4: 900 | F4: 1000 | G4: 1200
A5: 4 | B5: =($A5*Assumptions!$C$10*Assumptions!$C$41)*(1-Assumptions!$C$7)*B$4-($A5*Assumptions!$C$10*Assumptions!$C$41)*Assumptions!$C$8-'Cyclist Economics'!$B$10*Assumptions!$C$10-'Zone P&L'!$C$31 -> -449306.67 | C5: =($A5*Assumptions!$C$10*Assumptions!$C$41)*(1-Assumptions!$C$7)*C$4-($A5*Assumptions!$C$10*Assumptions!$C$41)*Assumptions!$C$8-'Cyclist Economics'!$B$10*Assumptions!$C$10-'Zone P&L'!$C$31 -> -346346.67 | D5: =($A5*Assumptions!$C$10*Assumptions!$C$41)*(1-Assumptions!$C$7)*D$4-($A5*Assumptions!$C$10*Assumptions!$C$41)*Assumptions!$C$8-'Cyclist Economics'!$B$10*Assumptions!$C$10-'Zone P&L'!$C$31 -> -243386.67 | E5: =($A5*Assumptions!$C$10*Assumptions!$C$41)*(1-Assumptions!$C$7)*E$4-($A5*Assumptions!$C$10*Assumptions!$C$41)*Assumptions!$C$8-'Cyclist Economics'!$B$10*Assumptions!$C$10-'Zone P&L'!$C$31 -> -140426.67 | F5: =($A5*Assumptions!$C$10*Assumptions!$C$41)*(1-Assumptions!$C$7)*F$4-($A5*Assumptions!$C$10*Assumptions!$C$41)*Assumptions!$C$8-'Cyclist Economics'!$B$10*Assumptions!$C$10-'Zone P&L'!$C$31 -> -37466.667 | G5: =($A5*Assumptions!$C$10*Assumptions!$C$41)*(1-Assumptions!$C$7)*G$4-($A5*Assumptions!$C$10*Assumptions!$C$41)*Assumptions!$C$8-'Cyclist Economics'!$B$10*Assumptions!$C$10-'Zone P&L'!$C$31 -> 168453.33
A6: 6 | B6: =($A6*Assumptions!$C$10*Assumptions!$C$41)*(1-Assumptions!$C$7)*B$4-($A6*Assumptions!$C$10*Assumptions!$C$41)*Assumptions!$C$8-'Cyclist Economics'!$B$10*Assumptions!$C$10-'Zone P&L'!$C$31 -> -145626.67 | C6: =($A6*Assumptions!$C$10*Assumptions!$C$41)*(1-Assumptions!$C$7)*C$4-($A6*Assumptions!$C$10*Assumptions!$C$41)*Assumptions!$C$8-'Cyclist Economics'!$B$10*Assumptions!$C$10-'Zone P&L'!$C$31 -> 8813.3333 | D6: =($A6*Assumptions!$C$10*Assumptions!$C$41)*(1-Assumptions!$C$7)*D$4-($A6*Assumptions!$C$10*Assumptions!$C$41)*Assumptions!$C$8-'Cyclist Economics'!$B$10*Assumptions!$C$10-'Zone P&L'!$C$31 -> 163253.33 | E6: =($A6*Assumptions!$C$10*Assumptions!$C$41)*(1-Assumptions!$C$7)*E$4-($A6*Assumptions!$C$10*Assumptions!$C$41)*Assumptions!$C$8-'Cyclist Economics'!$B$10*Assumptions!$C$10-'Zone P&L'!$C$31 -> 317693.33 | F6: =($A6*Assumptions!$C$10*Assumptions!$C$41)*(1-Assumptions!$C$7)*F$4-($A6*Assumptions!$C$10*Assumptions!$C$41)*Assumptions!$C$8-'Cyclist Economics'!$B$10*Assumptions!$C$10-'Zone P&L'!$C$31 -> 472133.33 | G6: =($A6*Assumptions!$C$10*Assumptions!$C$41)*(1-Assumptions!$C$7)*G$4-($A6*Assumptions!$C$10*Assumptions!$C$41)*Assumptions!$C$8-'Cyclist Economics'!$B$10*Assumptions!$C$10-'Zone P&L'!$C$31 -> 781013.33
A7: 8 | B7: =($A7*Assumptions!$C$10*Assumptions!$C$41)*(1-Assumptions!$C$7)*B$4-($A7*Assumptions!$C$10*Assumptions!$C$41)*Assumptions!$C$8-'Cyclist Economics'!$B$10*Assumptions!$C$10-'Zone P&L'!$C$31 -> 158053.33 | C7: =($A7*Assumptions!$C$10*Assumptions!$C$41)*(1-Assumptions!$C$7)*C$4-($A7*Assumptions!$C$10*Assumptions!$C$41)*Assumptions!$C$8-'Cyclist Economics'!$B$10*Assumptions!$C$10-'Zone P&L'!$C$31 -> 363973.33 | D7: =($A7*Assumptions!$C$10*Assumptions!$C$41)*(1-Assumptions!$C$7)*D$4-($A7*Assumptions!$C$10*Assumptions!$C$41)*Assumptions!$C$8-'Cyclist Economics'!$B$10*Assumptions!$C$10-'Zone P&L'!$C$31 -> 569893.33 | E7: =($A7*Assumptions!$C$10*Assumptions!$C$41)*(1-Assumptions!$C$7)*E$4-($A7*Assumptions!$C$10*Assumptions!$C$41)*Assumptions!$C$8-'Cyclist Economics'!$B$10*Assumptions!$C$10-'Zone P&L'!$C$31 -> 775813.33 | F7: =($A7*Assumptions!$C$10*Assumptions!$C$41)*(1-Assumptions!$C$7)*F$4-($A7*Assumptions!$C$10*Assumptions!$C$41)*Assumptions!$C$8-'Cyclist Economics'!$B$10*Assumptions!$C$10-'Zone P&L'!$C$31 -> 981733.33 | G7: =($A7*Assumptions!$C$10*Assumptions!$C$41)*(1-Assumptions!$C$7)*G$4-($A7*Assumptions!$C$10*Assumptions!$C$41)*Assumptions!$C$8-'Cyclist Economics'!$B$10*Assumptions!$C$10-'Zone P&L'!$C$31 -> 1393573.3
A8: 10 | B8: =($A8*Assumptions!$C$10*Assumptions!$C$41)*(1-Assumptions!$C$7)*B$4-($A8*Assumptions!$C$10*Assumptions!$C$41)*Assumptions!$C$8-'Cyclist Economics'!$B$10*Assumptions!$C$10-'Zone P&L'!$C$31 -> 461733.33 | C8: =($A8*Assumptions!$C$10*Assumptions!$C$41)*(1-Assumptions!$C$7)*C$4-($A8*Assumptions!$C$10*Assumptions!$C$41)*Assumptions!$C$8-'Cyclist Economics'!$B$10*Assumptions!$C$10-'Zone P&L'!$C$31 -> 719133.33 | D8: =($A8*Assumptions!$C$10*Assumptions!$C$41)*(1-Assumptions!$C$7)*D$4-($A8*Assumptions!$C$10*Assumptions!$C$41)*Assumptions!$C$8-'Cyclist Economics'!$B$10*Assumptions!$C$10-'Zone P&L'!$C$31 -> 976533.33 | E8: =($A8*Assumptions!$C$10*Assumptions!$C$41)*(1-Assumptions!$C$7)*E$4-($A8*Assumptions!$C$10*Assumptions!$C$41)*Assumptions!$C$8-'Cyclist Economics'!$B$10*Assumptions!$C$10-'Zone P&L'!$C$31 -> 1233933.3 | F8: =($A8*Assumptions!$C$10*Assumptions!$C$41)*(1-Assumptions!$C$7)*F$4-($A8*Assumptions!$C$10*Assumptions!$C$41)*Assumptions!$C$8-'Cyclist Economics'!$B$10*Assumptions!$C$10-'Zone P&L'!$C$31 -> 1491333.3 | G8: =($A8*Assumptions!$C$10*Assumptions!$C$41)*(1-Assumptions!$C$7)*G$4-($A8*Assumptions!$C$10*Assumptions!$C$41)*Assumptions!$C$8-'Cyclist Economics'!$B$10*Assumptions!$C$10-'Zone P&L'!$C$31 -> 2006133.3
A9: 12 | B9: =($A9*Assumptions!$C$10*Assumptions!$C$41)*(1-Assumptions!$C$7)*B$4-($A9*Assumptions!$C$10*Assumptions!$C$41)*Assumptions!$C$8-'Cyclist Economics'!$B$10*Assumptions!$C$10-'Zone P&L'!$C$31 -> 765413.33 | C9: =($A9*Assumptions!$C$10*Assumptions!$C$41)*(1-Assumptions!$C$7)*C$4-($A9*Assumptions!$C$10*Assumptions!$C$41)*Assumptions!$C$8-'Cyclist Economics'!$B$10*Assumptions!$C$10-'Zone P&L'!$C$31 -> 1074293.3 | D9: =($A9*Assumptions!$C$10*Assumptions!$C$41)*(1-Assumptions!$C$7)*D$4-($A9*Assumptions!$C$10*Assumptions!$C$41)*Assumptions!$C$8-'Cyclist Economics'!$B$10*Assumptions!$C$10-'Zone P&L'!$C$31 -> 1383173.3 | E9: =($A9*Assumptions!$C$10*Assumptions!$C$41)*(1-Assumptions!$C$7)*E$4-($A9*Assumptions!$C$10*Assumptions!$C$41)*Assumptions!$C$8-'Cyclist Economics'!$B$10*Assumptions!$C$10-'Zone P&L'!$C$31 -> 1692053.3 | F9: =($A9*Assumptions!$C$10*Assumptions!$C$41)*(1-Assumptions!$C$7)*F$4-($A9*Assumptions!$C$10*Assumptions!$C$41)*Assumptions!$C$8-'Cyclist Economics'!$B$10*Assumptions!$C$10-'Zone P&L'!$C$31 -> 2000933.3 | G9: =($A9*Assumptions!$C$10*Assumptions!$C$41)*(1-Assumptions!$C$7)*G$4-($A9*Assumptions!$C$10*Assumptions!$C$41)*Assumptions!$C$8-'Cyclist Economics'!$B$10*Assumptions!$C$10-'Zone P&L'!$C$31 -> 2618693.3
A10: 14 | B10: =($A10*Assumptions!$C$10*Assumptions!$C$41)*(1-Assumptions!$C$7)*B$4-($A10*Assumptions!$C$10*Assumptions!$C$41)*Assumptions!$C$8-'Cyclist Economics'!$B$10*Assumptions!$C$10-'Zone P&L'!$C$31 -> 1069093.3 | C10: =($A10*Assumptions!$C$10*Assumptions!$C$41)*(1-Assumptions!$C$7)*C$4-($A10*Assumptions!$C$10*Assumptions!$C$41)*Assumptions!$C$8-'Cyclist Economics'!$B$10*Assumptions!$C$10-'Zone P&L'!$C$31 -> 1429453.3 | D10: =($A10*Assumptions!$C$10*Assumptions!$C$41)*(1-Assumptions!$C$7)*D$4-($A10*Assumptions!$C$10*Assumptions!$C$41)*Assumptions!$C$8-'Cyclist Economics'!$B$10*Assumptions!$C$10-'Zone P&L'!$C$31 -> 1789813.3 | E10: =($A10*Assumptions!$C$10*Assumptions!$C$41)*(1-Assumptions!$C$7)*E$4-($A10*Assumptions!$C$10*Assumptions!$C$41)*Assumptions!$C$8-'Cyclist Economics'!$B$10*Assumptions!$C$10-'Zone P&L'!$C$31 -> 2150173.3 | F10: =($A10*Assumptions!$C$10*Assumptions!$C$41)*(1-Assumptions!$C$7)*F$4-($A10*Assumptions!$C$10*Assumptions!$C$41)*Assumptions!$C$8-'Cyclist Economics'!$B$10*Assumptions!$C$10-'Zone P&L'!$C$31 -> 2510533.3 | G10: =($A10*Assumptions!$C$10*Assumptions!$C$41)*(1-Assumptions!$C$7)*G$4-($A10*Assumptions!$C$10*Assumptions!$C$41)*Assumptions!$C$8-'Cyclist Economics'!$B$10*Assumptions!$C$10-'Zone P&L'!$C$31 -> 3231253.3
A11: 16 | B11: =($A11*Assumptions!$C$10*Assumptions!$C$41)*(1-Assumptions!$C$7)*B$4-($A11*Assumptions!$C$10*Assumptions!$C$41)*Assumptions!$C$8-'Cyclist Economics'!$B$10*Assumptions!$C$10-'Zone P&L'!$C$31 -> 1372773.3 | C11: =($A11*Assumptions!$C$10*Assumptions!$C$41)*(1-Assumptions!$C$7)*C$4-($A11*Assumptions!$C$10*Assumptions!$C$41)*Assumptions!$C$8-'Cyclist Economics'!$B$10*Assumptions!$C$10-'Zone P&L'!$C$31 -> 1784613.3 | D11: =($A11*Assumptions!$C$10*Assumptions!$C$41)*(1-Assumptions!$C$7)*D$4-($A11*Assumptions!$C$10*Assumptions!$C$41)*Assumptions!$C$8-'Cyclist Economics'!$B$10*Assumptions!$C$10-'Zone P&L'!$C$31 -> 2196453.3 | E11: =($A11*Assumptions!$C$10*Assumptions!$C$41)*(1-Assumptions!$C$7)*E$4-($A11*Assumptions!$C$10*Assumptions!$C$41)*Assumptions!$C$8-'Cyclist Economics'!$B$10*Assumptions!$C$10-'Zone P&L'!$C$31 -> 2608293.3 | F11: =($A11*Assumptions!$C$10*Assumptions!$C$41)*(1-Assumptions!$C$7)*F$4-($A11*Assumptions!$C$10*Assumptions!$C$41)*Assumptions!$C$8-'Cyclist Economics'!$B$10*Assumptions!$C$10-'Zone P&L'!$C$31 -> 3020133.3 | G11: =($A11*Assumptions!$C$10*Assumptions!$C$41)*(1-Assumptions!$C$7)*G$4-($A11*Assumptions!$C$10*Assumptions!$C$41)*Assumptions!$C$8-'Cyclist Economics'!$B$10*Assumptions!$C$10-'Zone P&L'!$C$31 -> 3843813.3
A13: Reading: find the row for the deliveries per cyclist per day the zone can realistically generate, then the lowest rate that is still positive. Capacity ceiling at 100% utilisation is on Cyclist Economics B15.
A15: Second table — break-even deliveries per cyclist per day by zone rate and cyclist wage
A16: Cyclist wage / month ↓ Zone rate → | B16: 600 | C16: 700 | D16: 800 | E16: 900 | F16: 1000 | G16: 1200
A17: 45000 | B17: =IF((B$16*(1-Assumptions!$C$7)-Assumptions!$C$8)<=0,0,(Assumptions!$C$10*($A17+('Cyclist Economics'!$B$10-'Cyclist Economics'!$B$5))+'Zone P&L'!$C$31)/(Assumptions!$C$10*Assumptions!$C$41*(B$16*(1-Assumptions!$C$7)-Assumptions!$C$8))) -> 5.9711978 | C17: =IF((C$16*(1-Assumptions!$C$7)-Assumptions!$C$8)<=0,0,(Assumptions!$C$10*($A17+('Cyclist Economics'!$B$10-'Cyclist Economics'!$B$5))+'Zone P&L'!$C$31)/(Assumptions!$C$10*Assumptions!$C$41*(C$16*(1-Assumptions!$C$7)-Assumptions!$C$8))) -> 5.1056801 | D17: =IF((D$16*(1-Assumptions!$C$7)-Assumptions!$C$8)<=0,0,(Assumptions!$C$10*($A17+('Cyclist Economics'!$B$10-'Cyclist Economics'!$B$5))+'Zone P&L'!$C$31)/(Assumptions!$C$10*Assumptions!$C$41*(D$16*(1-Assumptions!$C$7)-Assumptions!$C$8))) -> 4.4593088 | E17: =IF((E$16*(1-Assumptions!$C$7)-Assumptions!$C$8)<=0,0,(Assumptions!$C$10*($A17+('Cyclist Economics'!$B$10-'Cyclist Economics'!$B$5))+'Zone P&L'!$C$31)/(Assumptions!$C$10*Assumptions!$C$41*(E$16*(1-Assumptions!$C$7)-Assumptions!$C$8))) -> 3.958206 | F17: =IF((F$16*(1-Assumptions!$C$7)-Assumptions!$C$8)<=0,0,(Assumptions!$C$10*($A17+('Cyclist Economics'!$B$10-'Cyclist Economics'!$B$5))+'Zone P&L'!$C$31)/(Assumptions!$C$10*Assumptions!$C$41*(F$16*(1-Assumptions!$C$7)-Assumptions!$C$8))) -> 3.5583464 | G17: =IF((G$16*(1-Assumptions!$C$7)-Assumptions!$C$8)<=0,0,(Assumptions!$C$10*($A17+('Cyclist Economics'!$B$10-'Cyclist Economics'!$B$5))+'Zone P&L'!$C$31)/(Assumptions!$C$10*Assumptions!$C$41*(G$16*(1-Assumptions!$C$7)-Assumptions!$C$8))) -> 2.9602542
A18: 60000 | B18: =IF((B$16*(1-Assumptions!$C$7)-Assumptions!$C$8)<=0,0,(Assumptions!$C$10*($A18+('Cyclist Economics'!$B$10-'Cyclist Economics'!$B$5))+'Zone P&L'!$C$31)/(Assumptions!$C$10*Assumptions!$C$41*(B$16*(1-Assumptions!$C$7)-Assumptions!$C$8))) -> 6.9590797 | C18: =IF((C$16*(1-Assumptions!$C$7)-Assumptions!$C$8)<=0,0,(Assumptions!$C$10*($A18+('Cyclist Economics'!$B$10-'Cyclist Economics'!$B$5))+'Zone P&L'!$C$31)/(Assumptions!$C$10*Assumptions!$C$41*(C$16*(1-Assumptions!$C$7)-Assumptions!$C$8))) -> 5.9503698 | D18: =IF((D$16*(1-Assumptions!$C$7)-Assumptions!$C$8)<=0,0,(Assumptions!$C$10*($A18+('Cyclist Economics'!$B$10-'Cyclist Economics'!$B$5))+'Zone P&L'!$C$31)/(Assumptions!$C$10*Assumptions!$C$41*(D$16*(1-Assumptions!$C$7)-Assumptions!$C$8))) -> 5.1970621 | E18: =IF((E$16*(1-Assumptions!$C$7)-Assumptions!$C$8)<=0,0,(Assumptions!$C$10*($A18+('Cyclist Economics'!$B$10-'Cyclist Economics'!$B$5))+'Zone P&L'!$C$31)/(Assumptions!$C$10*Assumptions!$C$41*(E$16*(1-Assumptions!$C$7)-Assumptions!$C$8))) -> 4.6130563 | F18: =IF((F$16*(1-Assumptions!$C$7)-Assumptions!$C$8)<=0,0,(Assumptions!$C$10*($A18+('Cyclist Economics'!$B$10-'Cyclist Economics'!$B$5))+'Zone P&L'!$C$31)/(Assumptions!$C$10*Assumptions!$C$41*(F$16*(1-Assumptions!$C$7)-Assumptions!$C$8))) -> 4.1470434 | G18: =IF((G$16*(1-Assumptions!$C$7)-Assumptions!$C$8)<=0,0,(Assumptions!$C$10*($A18+('Cyclist Economics'!$B$10-'Cyclist Economics'!$B$5))+'Zone P&L'!$C$31)/(Assumptions!$C$10*Assumptions!$C$41*(G$16*(1-Assumptions!$C$7)-Assumptions!$C$8))) -> 3.4500022
A19: 75000 | B19: =IF((B$16*(1-Assumptions!$C$7)-Assumptions!$C$8)<=0,0,(Assumptions!$C$10*($A19+('Cyclist Economics'!$B$10-'Cyclist Economics'!$B$5))+'Zone P&L'!$C$31)/(Assumptions!$C$10*Assumptions!$C$41*(B$16*(1-Assumptions!$C$7)-Assumptions!$C$8))) -> 7.9469617 | C19: =IF((C$16*(1-Assumptions!$C$7)-Assumptions!$C$8)<=0,0,(Assumptions!$C$10*($A19+('Cyclist Economics'!$B$10-'Cyclist Economics'!$B$5))+'Zone P&L'!$C$31)/(Assumptions!$C$10*Assumptions!$C$41*(C$16*(1-Assumptions!$C$7)-Assumptions!$C$8))) -> 6.7950595 | D19: =IF((D$16*(1-Assumptions!$C$7)-Assumptions!$C$8)<=0,0,(Assumptions!$C$10*($A19+('Cyclist Economics'!$B$10-'Cyclist Economics'!$B$5))+'Zone P&L'!$C$31)/(Assumptions!$C$10*Assumptions!$C$41*(D$16*(1-Assumptions!$C$7)-Assumptions!$C$8))) -> 5.9348154 | E19: =IF((E$16*(1-Assumptions!$C$7)-Assumptions!$C$8)<=0,0,(Assumptions!$C$10*($A19+('Cyclist Economics'!$B$10-'Cyclist Economics'!$B$5))+'Zone P&L'!$C$31)/(Assumptions!$C$10*Assumptions!$C$41*(E$16*(1-Assumptions!$C$7)-Assumptions!$C$8))) -> 5.2679065 | F19: =IF((F$16*(1-Assumptions!$C$7)-Assumptions!$C$8)<=0,0,(Assumptions!$C$10*($A19+('Cyclist Economics'!$B$10-'Cyclist Economics'!$B$5))+'Zone P&L'!$C$31)/(Assumptions!$C$10*Assumptions!$C$41*(F$16*(1-Assumptions!$C$7)-Assumptions!$C$8))) -> 4.7357405 | G19: =IF((G$16*(1-Assumptions!$C$7)-Assumptions!$C$8)<=0,0,(Assumptions!$C$10*($A19+('Cyclist Economics'!$B$10-'Cyclist Economics'!$B$5))+'Zone P&L'!$C$31)/(Assumptions!$C$10*Assumptions!$C$41*(G$16*(1-Assumptions!$C$7)-Assumptions!$C$8))) -> 3.9397501
A20: 90000 | B20: =IF((B$16*(1-Assumptions!$C$7)-Assumptions!$C$8)<=0,0,(Assumptions!$C$10*($A20+('Cyclist Economics'!$B$10-'Cyclist Economics'!$B$5))+'Zone P&L'!$C$31)/(Assumptions!$C$10*Assumptions!$C$41*(B$16*(1-Assumptions!$C$7)-Assumptions!$C$8))) -> 8.9348437 | C20: =IF((C$16*(1-Assumptions!$C$7)-Assumptions!$C$8)<=0,0,(Assumptions!$C$10*($A20+('Cyclist Economics'!$B$10-'Cyclist Economics'!$B$5))+'Zone P&L'!$C$31)/(Assumptions!$C$10*Assumptions!$C$41*(C$16*(1-Assumptions!$C$7)-Assumptions!$C$8))) -> 7.6397492 | D20: =IF((D$16*(1-Assumptions!$C$7)-Assumptions!$C$8)<=0,0,(Assumptions!$C$10*($A20+('Cyclist Economics'!$B$10-'Cyclist Economics'!$B$5))+'Zone P&L'!$C$31)/(Assumptions!$C$10*Assumptions!$C$41*(D$16*(1-Assumptions!$C$7)-Assumptions!$C$8))) -> 6.6725687 | E20: =IF((E$16*(1-Assumptions!$C$7)-Assumptions!$C$8)<=0,0,(Assumptions!$C$10*($A20+('Cyclist Economics'!$B$10-'Cyclist Economics'!$B$5))+'Zone P&L'!$C$31)/(Assumptions!$C$10*Assumptions!$C$41*(E$16*(1-Assumptions!$C$7)-Assumptions!$C$8))) -> 5.9227568 | F20: =IF((F$16*(1-Assumptions!$C$7)-Assumptions!$C$8)<=0,0,(Assumptions!$C$10*($A20+('Cyclist Economics'!$B$10-'Cyclist Economics'!$B$5))+'Zone P&L'!$C$31)/(Assumptions!$C$10*Assumptions!$C$41*(F$16*(1-Assumptions!$C$7)-Assumptions!$C$8))) -> 5.3244375 | G20: =IF((G$16*(1-Assumptions!$C$7)-Assumptions!$C$8)<=0,0,(Assumptions!$C$10*($A20+('Cyclist Economics'!$B$10-'Cyclist Economics'!$B$5))+'Zone P&L'!$C$31)/(Assumptions!$C$10*Assumptions!$C$41*(G$16*(1-Assumptions!$C$7)-Assumptions!$C$8))) -> 4.4294981

Sheet Competitor Check
A1: Competitor Check — what a ₦3,000 meal over 2.5 km costs through each option
A2: Estimates from the Market & Competitor Research doc. Blue = input estimate; no Owerri operator publishes a tariff.
A4: Option | B4: Delivery fee off-peak (₦) | C4: Delivery fee peak (₦) | D4: Commission on food | E4: Commission (₦) on ₦3,000 | F4: Total cost off-peak (₦) | G4: Total cost peak (₦) | H4: Confidence / source
A5: Meal value (₦) | B5: 3000
A7: Informal rider | B7: 1500 | C7: 2000 | D7: 0 | E7: =D7*$B$5 -> 0 | F7: =B7+E7 -> 1500 | G7: =C7+E7 -> 2000 | H7: Low — inferred from original plan's ₦500–₦1,000 savings claim
A8: Bolt Send | B8: 1150 | C8: 1600 | D8: 0 | E8: =D8*$B$5 -> 0 | F8: =B8+E8 -> 1150 | G8: =C8+E8 -> 1600 | H8: Low–medium — scaled from Bolt ride tariffs (Lagos 2023, Abuja 2024); Send tariff not public
A9: Chowdeck | B9: 950 | C9: 1200 | D9: 0.25 | E9: =D9*$B$5 -> 750 | F9: =B9+E9 -> 1700 | G9: =C9+E9 -> 1950 | H9: Medium on commission (20–30% reported, Feb 2026 lawsuit); low on fee
A10: GoBuyMe | B10: 900 | C10: 1200 | D10: 0.03 | E10: =D10*$B$5 -> 90 | F10: =B10+E10 -> 990 | G10: =C10+E10 -> 1290 | H10: Low — commission 'from 3%' on marketing site; fee unknown
A11: Karryo | B11: 1000 | C11: 1300 | D11: 0 | E11: =D11*$B$5 -> 0 | F11: =B11+E11 -> 1000 | G11: =C11+E11 -> 1300 | H11: None — pre-launch; placeholder
A12: Airand (target) | B12: =Assumptions!$C$6 -> 900 | C12: =Assumptions!$C$6 -> 900 | D12: 0 | E12: =D12*$B$5 -> 0 | F12: =B12+E12 -> 900 | G12: =C12+E12 -> 900 | H12: Target from Assumptions P1; same price at peak
A14: Airand saving vs each option at peak (₦) | C14: % saving
A15: vs Informal rider | B15: =G7-$G$12 -> 1100 | C15: =IF(G7=0,0,B15/G7) -> 0.55
A16: vs Bolt Send | B16: =G8-$G$12 -> 700 | C16: =IF(G8=0,0,B16/G8) -> 0.4375
A17: vs Chowdeck | B17: =G9-$G$12 -> 1050 | C17: =IF(G9=0,0,B17/G9) -> 0.53846154
A18: vs GoBuyMe | B18: =G10-$G$12 -> 390 | C18: =IF(G10=0,0,B18/G10) -> 0.30232558
A19: vs Karryo | B19: =G11-$G$12 -> 400 | C19: =IF(G11=0,0,B19/G11) -> 0.30769231
